数字逻辑/DDCA_Project_1/DDCA_Project_1.srcs/sources_1/new/seven_seg_decoder.v
`timescale 1ns / 1ps
//////////////////////////////////////////////////////////////////////////////////
// Company: 
// Engineer: 
// 
// Create Date: 2026/04/26 13:55:31
// Design Name: 
// Module Name: seven_seg_decoder
// Project Name: 
// Target Devices: 
// Tool Versions: 
// Description: 
// 
// Dependencies: 
// 
// Revision:
// Revision 0.01 - File Created
// Additional Comments:
// 
//////////////////////////////////////////////////////////////////////////////////


module seven_seg_decoder (
    input wire clk,
    input wire rst,
    input wire [15:0] sum,
    input wire [2:0] state,
    output reg [6:0] seg,
    output reg [3:0] an
);

    reg [1:0] digit_sel;
    reg [14:0] refresh_cnt;
    reg [3:0] digit_val;
    
    // 刷新计数器，用于数码管动态扫描
    always @(posedge clk or posedge rst) begin
        if (rst) begin
            refresh_cnt <= 15'd0;
            digit_sel <= 2'd0;
        end else begin
            if (refresh_cnt == 15'd24999) begin
                refresh_cnt <= 15'd0;
                digit_sel <= digit_sel + 2'd1;
            end else begin
                refresh_cnt <= refresh_cnt + 15'd1;
            end
        end
    end
    
    // 选择当前要显示的位
    always @(*) begin
        case (digit_sel)
            2'd0: begin
                digit_val = sum[3:0];
                an = 4'b1110;
            end
            2'd1: begin
                digit_val = sum[7:4];
                an = 4'b1101;
            end
            2'd2: begin
                digit_val = sum[11:8];
                an = 4'b1011;
            end
            2'd3: begin
                digit_val = sum[15:12];
                an = 4'b0111;
            end
            default: begin
                digit_val = 4'd0;
                an = 4'b1111;
            end
        endcase
    end
    
    // 七段译码（共阳极）
    always @(*) begin
        case (digit_val)
            4'h0: seg = 7'b1000000; // 0
            4'h1: seg = 7'b1111001; // 1
            4'h2: seg = 7'b0100100; // 2
            4'h3: seg = 7'b0110000; // 3
            4'h4: seg = 7'b0011001; // 4
            4'h5: seg = 7'b0010010; // 5
            4'h6: seg = 7'b0000010; // 6
            4'h7: seg = 7'b1111000; // 7
            4'h8: seg = 7'b0000000; // 8
            4'h9: seg = 7'b0010000; // 9
            4'ha: seg = 7'b0001000; // A
            4'hb: seg = 7'b0000011; // B
            4'hc: seg = 7'b1000110; // C
            4'hd: seg = 7'b0100001; // D
            4'he: seg = 7'b0000110; // E
            4'hf: seg = 7'b0001110; // F
            default: seg = 7'b1111111;
        endcase
    end

endmodule

数字逻辑/DDCA_Project_1/DDCA_Project_1.srcs/sources_1/new/accumulator.v
`timescale 1ns / 1ps
//////////////////////////////////////////////////////////////////////////////////
// Company: 
// Engineer: 
// 
// Create Date: 2026/04/26 13:55:31
// Design Name: 
// Module Name: accumulator
// Project Name: 
// Target Devices: 
// Tool Versions: 
// Description: 
// 
// Dependencies: 
// 
// Revision:
// Revision 0.01 - File Created
// Additional Comments:
// 
//////////////////////////////////////////////////////////////////////////////////


module accumulator (
    input wire clk,
    input wire rst,
    output reg [6:0] addr,
    input wire [7:0] data_in,
    output reg [15:0] sum,
    output reg [2:0] state
);

    // 状态编码
    localparam IDLE     = 3'b000;
    localparam READ     = 3'b001;
    localparam ACCUM    = 3'b010;
    localparam DONE     = 3'b011;
    
    reg [6:0] cnt;
    
    always @(posedge clk or posedge rst) begin
        if (rst) begin
            addr <= 7'd0;
            sum <= 16'd0;
            cnt <= 7'd0;
            state <= IDLE;
        end else begin
            case (state)
                IDLE: begin
                    addr <= 7'd0;
                    sum <= 16'd0;
                    cnt <= 7'd0;
                    state <= READ;
                end
                
                READ: begin
                    state <= ACCUM;
                end
                
                ACCUM: begin
                    // 累加当前读出的数据
                    sum <= sum + {8'd0, data_in};
                    
                    if (cnt == 7'd127) begin
                        state <= DONE;
                    end else begin
                        cnt <= cnt + 7'd1;
                        addr <= addr + 7'd1;
                        state <= READ;
                    end
                end
                
                DONE: begin
                    // 保持结果，不再变化
                    state <= DONE;
                end
                
                default: begin
                    state <= IDLE;
                end
            endcase
        end
    end

endmodule

数字逻辑/DDCA_Project_1/DDCA_Project_1.srcs/sources_1/new/ram_128x8.v
`timescale 1ns / 1ps
//////////////////////////////////////////////////////////////////////////////////
// Company: 
// Engineer: 
// 
// Create Date: 2026/04/26 13:55:31
// Design Name: 
// Module Name: ram_128x8
// Project Name: 
// Target Devices: 
// Tool Versions: 
// Description: 
// 
// Dependencies: 
// 
// Revision:
// Revision 0.01 - File Created
// Additional Comments:
// 
//////////////////////////////////////////////////////////////////////////////////


module ram_128x8 (
    input wire clk,
    input wire [6:0] addr,
    output reg [7:0] dout
);

    reg [7:0] mem [0:127];
    
    // 从文件初始化存储器
    initial begin
        $readmemh("rams_init_file.data", mem);
    end
    
    // 同步读操作
    always @(posedge clk) begin
        dout <= mem[addr];
    end

endmodule

大一/数字逻辑/DDCA_Project_1/DDCA_Project_1.srcs/sources_1/new/top_level.v
`timescale 1ns / 1ps
//////////////////////////////////////////////////////////////////////////////////
// Company: 
// Engineer: 
// 
// Create Date: 2026/04/26 13:55:30
// Design Name: 
// Module Name: top_level
// Project Name: 
// Target Devices: 
// Tool Versions: 
// Description: 
// 
// Dependencies: 
// 
// Revision:
// Revision 0.01 - File Created
// Additional Comments:
// 
//////////////////////////////////////////////////////////////////////////////////

module top_level (
    input wire clk,
    input wire rst,
    output wire [6:0] seg,
    output wire [3:0] an
);

    wire [6:0] addr;
    wire [7:0] data_out;
    wire [15:0] sum;
    wire [2:0] state;
    
    // 例化存储器
    ram_128x8 u_ram (
        .clk(clk),
        .addr(addr),
        .dout(data_out)
    );
    
    // 例化累加器
    accumulator u_acc (
        .clk(clk),
        .rst(rst),
        .addr(addr),
        .data_in(data_out),
        .sum(sum),
        .state(state)
    );
    
    // 例化七段译码器
    seven_seg_decoder u_seg (
        .clk(clk),
        .rst(rst),
        .sum(sum),
        .state(state),
        .seg(seg),
        .an(an)
    );

endmodule

数字逻辑/DDCA_Project_1/DDCA_Project_1.srcs/sim_1/new/tb_top_level.v
`timescale 1ns / 1ps
//////////////////////////////////////////////////////////////////////////////////
// Company: 
// Engineer: 
// 
// Create Date: 2026/04/26 13:59:05
// Design Name: 
// Module Name: tb_top_level
// Project Name: 
// Target Devices: 
// Tool Versions: 
// Description: 
// 
// Dependencies: 
// 
// Revision:
// Revision 0.01 - File Created
// Additional Comments:
// 
//////////////////////////////////////////////////////////////////////////////////


module tb_top_level;

    reg clk;
    reg rst;
    wire [6:0] seg;
    wire [3:0] an;
    
    // 内部信号用于观察
    wire [6:0] addr;
    wire [7:0] data_out;
    wire [15:0] sum;
    wire [2:0] state;
    
    // 例化顶层模块
    top_level u_top (
        .clk(clk),
        .rst(rst),
        .seg(seg),
        .an(an)
    );
    
    // 通过层次路径访问内部信号
    assign addr = u_top.u_acc.addr;
    assign data_out = u_top.u_ram.dout;
    assign sum = u_top.u_acc.sum;
    assign state = u_top.u_acc.state;
    
    // 100MHz时钟产生
    initial begin
        clk = 0;
        forever #5 clk = ~clk;  // 周期10ns = 100MHz
    end
    
    // 复位信号：第5ns有效，15ns结束
    initial begin
        rst = 0;
        #5 rst = 1;
        #10 rst = 0;
    end
    
    // 波形转储
    initial begin
        $dumpfile("wave.vcd");
        $dumpvars(0, tb_top_level);
    end
    
    // 140个周期后结束仿真
    initial begin
        #1400 $finish;  // 140 * 10ns = 1400ns
    end
    
    // 监控输出
    initial begin
        $monitor("Time=%0t ns | clk=%b rst=%b addr=%d data=%h state=%d sum=%h",
                 $time, clk, rst, addr, data_out, state, sum);
    end

endmodule

数字逻辑/DDCA_Project_1/DDCA_Project_1.sim/sim_1/behav/xsim/wave.vcd
$date
   Sun Apr 26 14:12:31 2026
$end

$version
  2025.2
  $dumpfile ("wave.vcd") 
$end

$timescale
  1ps
$end

$scope module tb_top_level $end
$var reg 1 ! clk $end
$var reg 1 " rst $end
$var wire 7 # seg [6:0] $end
$var wire 4 $ an [3:0] $end
$var wire 7 % addr [6:0] $end
$var wire 8 & data_out [7:0] $end
$var wire 16 ' sum [15:0] $end
$var wire 3 ( state [2:0] $end
$scope module u_top $end
$var wire 1 ) clk $end
$var wire 1 * rst $end
$var wire 7 # seg [6:0] $end
$var wire 4 $ an [3:0] $end
$var wire 7 + addr [6:0] $end
$var wire 8 , data_out [7:0] $end
$var wire 16 - sum [15:0] $end
$var wire 3 . state [2:0] $end
$scope module u_ram $end
$var wire 1 ) clk $end
$var wire 7 + addr [6:0] $end
$var reg 8 / dout [7:0] $end
$upscope $end
$scope module u_acc $end
$var wire 1 ) clk $end
$var wire 1 * rst $end
$var reg 7 0 addr [6:0] $end
$var wire 8 , data_in [7:0] $end
$var reg 16 1 sum [15:0] $end
$var reg 3 2 state [2:0] $end
$var reg 7 3 cnt [6:0] $end
$upscope $end
$scope module u_seg $end
$var wire 1 ) clk $end
$var wire 1 * rst $end
$var wire 16 - sum [15:0] $end
$var wire 3 . state [2:0] $end
$var reg 7 4 seg [6:0] $end
$var reg 4 5 an [3:0] $end
$var reg 2 6 digit_sel [1:0] $end
$var reg 15 7 refresh_cnt [14:0] $end
$var reg 4 8 digit_val [3:0] $end
$upscope $end
$upscope $end
$upscope $end
$enddefinitions $end

#0
$dumpvars
0!
0"
bx #
bx $
bx %
bx &
bx '
bx (
0)
0*
bx +
bx ,
bx -
bx .
bx /
bx 0
bx 1
bx 2
bx 3
bx 4
bx 5
bx 6
bx 7
bx 8
$end

#5000
1!
1"
b1000000 #
b1110 $
b0 %
b0 '
b0 (
1)
1*
b0 +
b0 -
b0 .
b0 0
b0 1
b0 2
b0 3
b1000000 4
b1110 5
b0 6
b0 7
b0 8

#10000
0!
0)

#15000
1!
0"
b10 &
b1 (
1)
0*
b10 ,
b1 .
b10 /
b1 2
b1 7

#20000
0!
0)

#25000
1!
b10 (
1)
b10 .
b10 2
b10 7

#30000
0!
0)

#35000
1!
b100100 #
b1 %
b10 '
b1 (
1)
b1 +
b10 -
b1 .
b1 0
b10 1
b1 2
b1 3
b100100 4
b11 7
b10 8

#40000
0!
0)

#45000
1!
b10 (
1)
b10 .
b10 2
b100 7

#50000
0!
0)

#55000
1!
b11001 #
b10 %
b100 '
b1 (
1)
b10 +
b100 -
b1 .
b10 0
b100 1
b1 2
b10 3
b11001 4
b101 7
b100 8

#60000
0!
0)

#65000
1!
b10 (
1)
b10 .
b10 2
b110 7

#70000
0!
0)

#75000
1!
b10 #
b11 %
b110 '
b1 (
1)
b11 +
b110 -
b1 .
b11 0
b110 1
b1 2
b11 3
b10 4
b111 7
b110 8

#80000
0!
0)

#85000
1!
b10 (
1)
b10 .
b10 2
b1000 7

#90000
0!
0)

#95000
1!
b0 #
b100 %
b1000 '
b1 (
1)
b100 +
b1000 -
b1 .
b100 0
b1000 1
b1 2
b100 3
b0 4
b1001 7
b1000 8

#100000
0!
0)

#105000
1!
b10 (
1)
b10 .
b10 2
b1010 7

#110000
0!
0)

#115000
1!
b1000 #
b101 %
b1010 '
b1 (
1)
b101 +
b1010 -
b1 .
b101 0
b1010 1
b1 2
b101 3
b1000 4
b1011 7
b1010 8

#120000
0!
0)

#125000
1!
b10 (
1)
b10 .
b10 2
b1100 7

#130000
0!
0)

#135000
1!
b1000110 #
b110 %
b1100 '
b1 (
1)
b110 +
b1100 -
b1 .
b110 0
b1100 1
b1 2
b110 3
b1000110 4
b1101 7
b1100 8

#140000
0!
0)

#145000
1!
b10 (
1)
b10 .
b10 2
b1110 7

#150000
0!
0)

#155000
1!
b110 #
b111 %
b1110 '
b1 (
1)
b111 +
b1110 -
b1 .
b111 0
b1110 1
b1 2
b111 3
b110 4
b1111 7
b1110 8

#160000
0!
0)

#165000
1!
b10 (
1)
b10 .
b10 2
b10000 7

#170000
0!
0)

#175000
1!
b1000000 #
b1000 %
b10000 '
b1 (
1)
b1000 +
b10000 -
b1 .
b1000 0
b10000 1
b1 2
b1000 3
b1000000 4
b10001 7
b0 8

#180000
0!
0)

#185000
1!
b10 (
1)
b10 .
b10 2
b10010 7

#190000
0!
0)

#195000
1!
b100100 #
b1001 %
b10010 '
b1 (
1)
b1001 +
b10010 -
b1 .
b1001 0
b10010 1
b1 2
b1001 3
b100100 4
b10011 7
b10 8

#200000
0!
0)

#205000
1!
b10 (
1)
b10 .
b10 2
b10100 7

#210000
0!
0)

#215000
1!
b11001 #
b1010 %
b10100 '
b1 (
1)
b1010 +
b10100 -
b1 .
b1010 0
b10100 1
b1 2
b1010 3
b11001 4
b10101 7
b100 8

#220000
0!
0)

#225000
1!
b10 (
1)
b10 .
b10 2
b10110 7

#230000
0!
0)

#235000
1!
b10 #
b1011 %
b10110 '
b1 (
1)
b1011 +
b10110 -
b1 .
b1011 0
b10110 1
b1 2
b1011 3
b10 4
b10111 7
b110 8

#240000
0!
0)

#245000
1!
b10 (
1)
b10 .
b10 2
b11000 7

#250000
0!
0)

#255000
1!
b0 #
b1100 %
b11000 '
b1 (
1)
b1100 +
b11000 -
b1 .
b1100 0
b11000 1
b1 2
b1100 3
b0 4
b11001 7
b1000 8

#260000
0!
0)

#265000
1!
b10 (
1)
b10 .
b10 2
b11010 7

#270000
0!
0)

#275000
1!
b1000 #
b1101 %
b11010 '
b1 (
1)
b1101 +
b11010 -
b1 .
b1101 0
b11010 1
b1 2
b1101 3
b1000 4
b11011 7
b1010 8

#280000
0!
0)

#285000
1!
b10 (
1)
b10 .
b10 2
b11100 7

#290000
0!
0)

#295000
1!
b1000110 #
b1110 %
b11100 '
b1 (
1)
b1110 +
b11100 -
b1 .
b1110 0
b11100 1
b1 2
b1110 3
b1000110 4
b11101 7
b1100 8

#300000
0!
0)

#305000
1!
b10 (
1)
b10 .
b10 2
b11110 7

#310000
0!
0)

#315000
1!
b110 #
b1111 %
b11110 '
b1 (
1)
b1111 +
b11110 -
b1 .
b1111 0
b11110 1
b1 2
b1111 3
b110 4
b11111 7
b1110 8

#320000
0!
0)

#325000
1!
b10 (
1)
b10 .
b10 2
b100000 7

#330000
0!
0)

#335000
1!
b1000000 #
b10000 %
b100000 '
b1 (
1)
b10000 +
b100000 -
b1 .
b10000 0
b100000 1
b1 2
b10000 3
b1000000 4
b100001 7
b0 8

#340000
0!
0)

#345000
1!
b10 (
1)
b10 .
b10 2
b100010 7

#350000
0!
0)

#355000
1!
b100100 #
b10001 %
b100010 '
b1 (
1)
b10001 +
b100010 -
b1 .
b10001 0
b100010 1
b1 2
b10001 3
b100100 4
b100011 7
b10 8

#360000
0!
0)

#365000
1!
b10 (
1)
b10 .
b10 2
b100100 7

#370000
0!
0)

#375000
1!
b11001 #
b10010 %
b100100 '
b1 (
1)
b10010 +
b100100 -
b1 .
b10010 0
b100100 1
b1 2
b10010 3
b11001 4
b100101 7
b100 8

#380000
0!
0)

#385000
1!
b10 (
1)
b10 .
b10 2
b100110 7

#390000
0!
0)

#395000
1!
b10 #
b10011 %
b100110 '
b1 (
1)
b10011 +
b100110 -
b1 .
b10011 0
b100110 1
b1 2
b10011 3
b10 4
b100111 7
b110 8

#400000
0!
0)

#405000
1!
b10 (
1)
b10 .
b10 2
b101000 7

#410000
0!
0)

#415000
1!
b0 #
b10100 %
b101000 '
b1 (
1)
b10100 +
b101000 -
b1 .
b10100 0
b101000 1
b1 2
b10100 3
b0 4
b101001 7
b1000 8

#420000
0!
0)

#425000
1!
b10 (
1)
b10 .
b10 2
b101010 7

#430000
0!
0)

#435000
1!
b1000 #
b10101 %
b101010 '
b1 (
1)
b10101 +
b101010 -
b1 .
b10101 0
b101010 1
b1 2
b10101 3
b1000 4
b101011 7
b1010 8

#440000
0!
0)

#445000
1!
b10 (
1)
b10 .
b10 2
b101100 7

#450000
0!
0)

#455000
1!
b1000110 #
b10110 %
b101100 '
b1 (
1)
b10110 +
b101100 -
b1 .
b10110 0
b101100 1
b1 2
b10110 3
b1000110 4
b101101 7
b1100 8

#460000
0!
0)

#465000
1!
b10 (
1)
b10 .
b10 2
b101110 7

#470000
0!
0)

#475000
1!
b110 #
b10111 %
b101110 '
b1 (
1)
b10111 +
b101110 -
b1 .
b10111 0
b101110 1
b1 2
b10111 3
b110 4
b101111 7
b1110 8

#480000
0!
0)

#485000
1!
b10 (
1)
b10 .
b10 2
b110000 7

#490000
0!
0)

#495000
1!
b1000000 #
b11000 %
b110000 '
b1 (
1)
b11000 +
b110000 -
b1 .
b11000 0
b110000 1
b1 2
b11000 3
b1000000 4
b110001 7
b0 8

#500000
0!
0)

#505000
1!
b10 (
1)
b10 .
b10 2
b110010 7

#510000
0!
0)

#515000
1!
b100100 #
b11001 %
b110010 '
b1 (
1)
b11001 +
b110010 -
b1 .
b11001 0
b110010 1
b1 2
b11001 3
b100100 4
b110011 7
b10 8

#520000
0!
0)

#525000
1!
b10 (
1)
b10 .
b10 2
b110100 7

#530000
0!
0)

#535000
1!
b11001 #
b11010 %
b110100 '
b1 (
1)
b11010 +
b110100 -
b1 .
b11010 0
b110100 1
b1 2
b11010 3
b11001 4
b110101 7
b100 8

#540000
0!
0)

#545000
1!
b10 (
1)
b10 .
b10 2
b110110 7

#550000
0!
0)

#555000
1!
b10 #
b11011 %
b110110 '
b1 (
1)
b11011 +
b110110 -
b1 .
b11011 0
b110110 1
b1 2
b11011 3
b10 4
b110111 7
b110 8

#560000
0!
0)

#565000
1!
b10 (
1)
b10 .
b10 2
b111000 7

#570000
0!
0)

#575000
1!
b0 #
b11100 %
b111000 '
b1 (
1)
b11100 +
b111000 -
b1 .
b11100 0
b111000 1
b1 2
b11100 3
b0 4
b111001 7
b1000 8

#580000
0!
0)

#585000
1!
b10 (
1)
b10 .
b10 2
b111010 7

#590000
0!
0)

#595000
1!
b1000 #
b11101 %
b111010 '
b1 (
1)
b11101 +
b111010 -
b1 .
b11101 0
b111010 1
b1 2
b11101 3
b1000 4
b111011 7
b1010 8

#600000
0!
0)

#605000
1!
b10 (
1)
b10 .
b10 2
b111100 7

#610000
0!
0)

#615000
1!
b1000110 #
b11110 %
b111100 '
b1 (
1)
b11110 +
b111100 -
b1 .
b11110 0
b111100 1
b1 2
b11110 3
b1000110 4
b111101 7
b1100 8

#620000
0!
0)

#625000
1!
b10 (
1)
b10 .
b10 2
b111110 7

#630000
0!
0)

#635000
1!
b110 #
b11111 %
b111110 '
b1 (
1)
b11111 +
b111110 -
b1 .
b11111 0
b111110 1
b1 2
b11111 3
b110 4
b111111 7
b1110 8

#640000
0!
0)

#645000
1!
b10 (
1)
b10 .
b10 2
b1000000 7

#650000
0!
0)

#655000
1!
b1000000 #
b100000 %
b1000000 '
b1 (
1)
b100000 +
b1000000 -
b1 .
b100000 0
b1000000 1
b1 2
b100000 3
b1000000 4
b1000001 7
b0 8

#660000
0!
0)

#665000
1!
b10 (
1)
b10 .
b10 2
b1000010 7

#670000
0!
0)

#675000
1!
b100100 #
b100001 %
b1000010 '
b1 (
1)
b100001 +
b1000010 -
b1 .
b100001 0
b1000010 1
b1 2
b100001 3
b100100 4
b1000011 7
b10 8

#680000
0!
0)

#685000
1!
b10 (
1)
b10 .
b10 2
b1000100 7

#690000
0!
0)

#695000
1!
b11001 #
b100010 %
b1000100 '
b1 (
1)
b100010 +
b1000100 -
b1 .
b100010 0
b1000100 1
b1 2
b100010 3
b11001 4
b1000101 7
b100 8

#700000
0!
0)

#705000
1!
b10 (
1)
b10 .
b10 2
b1000110 7

#710000
0!
0)

#715000
1!
b10 #
b100011 %
b1000110 '
b1 (
1)
b100011 +
b1000110 -
b1 .
b100011 0
b1000110 1
b1 2
b100011 3
b10 4
b1000111 7
b110 8

#720000
0!
0)

#725000
1!
b10 (
1)
b10 .
b10 2
b1001000 7

#730000
0!
0)

#735000
1!
b0 #
b100100 %
b1001000 '
b1 (
1)
b100100 +
b1001000 -
b1 .
b100100 0
b1001000 1
b1 2
b100100 3
b0 4
b1001001 7
b1000 8

#740000
0!
0)

#745000
1!
b10 (
1)
b10 .
b10 2
b1001010 7

#750000
0!
0)

#755000
1!
b1000 #
b100101 %
b1001010 '
b1 (
1)
b100101 +
b1001010 -
b1 .
b100101 0
b1001010 1
b1 2
b100101 3
b1000 4
b1001011 7
b1010 8

#760000
0!
0)

#765000
1!
b10 (
1)
b10 .
b10 2
b1001100 7

#770000
0!
0)

#775000
1!
b1000110 #
b100110 %
b1001100 '
b1 (
1)
b100110 +
b1001100 -
b1 .
b100110 0
b1001100 1
b1 2
b100110 3
b1000110 4
b1001101 7
b1100 8

#780000
0!
0)

#785000
1!
b10 (
1)
b10 .
b10 2
b1001110 7

#790000
0!
0)

#795000
1!
b110 #
b100111 %
b1001110 '
b1 (
1)
b100111 +
b1001110 -
b1 .
b100111 0
b1001110 1
b1 2
b100111 3
b110 4
b1001111 7
b1110 8

#800000
0!
0)

#805000
1!
b10 (
1)
b10 .
b10 2
b1010000 7

#810000
0!
0)

#815000
1!
b1000000 #
b101000 %
b1010000 '
b1 (
1)
b101000 +
b1010000 -
b1 .
b101000 0
b1010000 1
b1 2
b101000 3
b1000000 4
b1010001 7
b0 8

#820000
0!
0)

#825000
1!
b10 (
1)
b10 .
b10 2
b1010010 7

#830000
0!
0)

#835000
1!
b100100 #
b101001 %
b1010010 '
b1 (
1)
b101001 +
b1010010 -
b1 .
b101001 0
b1010010 1
b1 2
b101001 3
b100100 4
b1010011 7
b10 8

#840000
0!
0)

#845000
1!
b10 (
1)
b10 .
b10 2
b1010100 7

#850000
0!
0)

#855000
1!
b11001 #
b101010 %
b1010100 '
b1 (
1)
b101010 +
b1010100 -
b1 .
b101010 0
b1010100 1
b1 2
b101010 3
b11001 4
b1010101 7
b100 8

#860000
0!
0)

#865000
1!
b10 (
1)
b10 .
b10 2
b1010110 7

#870000
0!
0)

#875000
1!
b10 #
b101011 %
b1010110 '
b1 (
1)
b101011 +
b1010110 -
b1 .
b101011 0
b1010110 1
b1 2
b101011 3
b10 4
b1010111 7
b110 8

#880000
0!
0)

#885000
1!
b10 (
1)
b10 .
b10 2
b1011000 7

#890000
0!
0)

#895000
1!
b0 #
b101100 %
b1011000 '
b1 (
1)
b101100 +
b1011000 -
b1 .
b101100 0
b1011000 1
b1 2
b101100 3
b0 4
b1011001 7
b1000 8

#900000
0!
0)

#905000
1!
b10 (
1)
b10 .
b10 2
b1011010 7

#910000
0!
0)

#915000
1!
b1000 #
b101101 %
b1011010 '
b1 (
1)
b101101 +
b1011010 -
b1 .
b101101 0
b1011010 1
b1 2
b101101 3
b1000 4
b1011011 7
b1010 8

#920000
0!
0)

#925000
1!
b10 (
1)
b10 .
b10 2
b1011100 7

#930000
0!
0)

#935000
1!
b1000110 #
b101110 %
b1011100 '
b1 (
1)
b101110 +
b1011100 -
b1 .
b101110 0
b1011100 1
b1 2
b101110 3
b1000110 4
b1011101 7
b1100 8

#940000
0!
0)

#945000
1!
b10 (
1)
b10 .
b10 2
b1011110 7

#950000
0!
0)

#955000
1!
b110 #
b101111 %
b1011110 '
b1 (
1)
b101111 +
b1011110 -
b1 .
b101111 0
b1011110 1
b1 2
b101111 3
b110 4
b1011111 7
b1110 8

#960000
0!
0)

#965000
1!
b10 (
1)
b10 .
b10 2
b1100000 7

#970000
0!
0)

#975000
1!
b1000000 #
b110000 %
b1100000 '
b1 (
1)
b110000 +
b1100000 -
b1 .
b110000 0
b1100000 1
b1 2
b110000 3
b1000000 4
b1100001 7
b0 8

#980000
0!
0)

#985000
1!
b10 (
1)
b10 .
b10 2
b1100010 7

#990000
0!
0)

#995000
1!
b100100 #
b110001 %
b1100010 '
b1 (
1)
b110001 +
b1100010 -
b1 .
b110001 0
b1100010 1
b1 2
b110001 3
b100100 4
b1100011 7
b10 8

